{
  "content": [
    {
      "content": null,
      "created": "2025-12-23T21:33:23.508459Z",
      "format": null,
      "hash": null,
      "hash_algorithm": null,
      "last_modified": "2025-12-23T21:33:18.875488Z",
      "mimetype": null,
      "name": "plot_adjusted_for_chance_measures.ipynb",
      "path": "auto_examples/cluster/plot_adjusted_for_chance_measures.ipynb",
      "size": 11879,
      "type": "notebook",
      "writable": true
    },
    {
      "content": null,
      "created": "2025-12-23T21:33:23.508459Z",
      "format": null,
      "hash": null,
      "hash_algorithm": null,
      "last_modified": "2025-12-23T21:33:18.876488Z",
      "mimetype": null,
      "name": "plot_affinity_propagation.ipynb",
      "path": "auto_examples/cluster/plot_affinity_propagation.ipynb",
      "size": 4615,
      "type": "notebook",
      "writable": true
    },
    {
      "content": null,
      "created": "2025-12-23T21:33:23.508459Z",
      "format": null,
      "hash": null,
      "hash_algorithm": null,
      "last_modified": "2025-12-23T21:33:18.876488Z",
      "mimetype": null,
      "name": "plot_agglomerative_clustering_metrics.ipynb",
      "path": "auto_examples/cluster/plot_agglomerative_clustering_metrics.ipynb",
      "size": 6521,
      "type": "notebook",
      "writable": true
    },
    {
      "content": null,
      "created": "2025-12-23T21:33:23.509459Z",
      "format": null,
      "hash": null,
      "hash_algorithm": null,
      "last_modified": "2025-12-23T21:33:18.877488Z",
      "mimetype": null,
      "name": "plot_agglomerative_dendrogram.ipynb",
      "path": "auto_examples/cluster/plot_agglomerative_dendrogram.ipynb",
      "size": 3186,
      "type": "notebook",
      "writable": true
    },
    {
      "content": null,
      "created": "2025-12-23T21:33:23.509459Z",
      "format": null,
      "hash": null,
      "hash_algorithm": null,
      "last_modified": "2025-12-23T21:33:18.877488Z",
      "mimetype": null,
      "name": "plot_birch_vs_minibatchkmeans.ipynb",
      "path": "auto_examples/cluster/plot_birch_vs_minibatchkmeans.ipynb",
      "size": 5427,
      "type": "notebook",
      "writable": true
    },
    {
      "content": null,
      "created": "2025-12-23T21:33:23.509459Z",
      "format": null,
      "hash": null,
      "hash_algorithm": null,
      "last_modified": "2025-12-23T21:33:18.878488Z",
      "mimetype": null,
      "name": "plot_bisect_kmeans.ipynb",
      "path": "auto_examples/cluster/plot_bisect_kmeans.ipynb",
      "size": 3579,
      "type": "notebook",
      "writable": true
    },
    {
      "content": null,
      "created": "2025-12-23T21:33:23.510459Z",
      "format": null,
      "hash": null,
      "hash_algorithm": null,
      "last_modified": "2025-12-23T21:33:18.878488Z",
      "mimetype": null,
      "name": "plot_cluster_comparison.ipynb",
      "path": "auto_examples/cluster/plot_cluster_comparison.ipynb",
      "size": 10516,
      "type": "notebook",
      "writable": true
    },
    {
      "content": null,
      "created": "2025-12-23T21:33:23.510459Z",
      "format": null,
      "hash": null,
      "hash_algorithm": null,
      "last_modified": "2025-12-23T21:33:18.879488Z",
      "mimetype": null,
      "name": "plot_coin_segmentation.ipynb",
      "path": "auto_examples/cluster/plot_coin_segmentation.ipynb",
      "size": 5762,
      "type": "notebook",
      "writable": true
    },
    {
      "content": null,
      "created": "2025-12-23T21:33:23.510459Z",
      "format": null,
      "hash": null,
      "hash_algorithm": null,
      "last_modified": "2025-12-23T21:33:18.879488Z",
      "mimetype": null,
      "name": "plot_coin_ward_segmentation.ipynb",
      "path": "auto_examples/cluster/plot_coin_ward_segmentation.ipynb",
      "size": 5199,
      "type": "notebook",
      "writable": true
    },
    {
      "content": null,
      "created": "2025-12-23T21:33:23.511459Z",
      "format": null,
      "hash": null,
      "hash_algorithm": null,
      "last_modified": "2025-12-23T21:33:18.880488Z",
      "mimetype": null,
      "name": "plot_dbscan.ipynb",
      "path": "auto_examples/cluster/plot_dbscan.ipynb",
      "size": 7016,
      "type": "notebook",
      "writable": true
    },
    {
      "content": null,
      "created": "2025-12-23T21:33:23.511459Z",
      "format": null,
      "hash": null,
      "hash_algorithm": null,
      "last_modified": "2025-12-23T21:33:18.880488Z",
      "mimetype": null,
      "name": "plot_dict_face_patches.ipynb",
      "path": "auto_examples/cluster/plot_dict_face_patches.ipynb",
      "size": 5190,
      "type": "notebook",
      "writable": true
    },
    {
      "content": null,
      "created": "2025-12-23T21:33:23.511459Z",
      "format": null,
      "hash": null,
      "hash_algorithm": null,
      "last_modified": "2025-12-23T21:33:18.881488Z",
      "mimetype": null,
      "name": "plot_digits_agglomeration.ipynb",
      "path": "auto_examples/cluster/plot_digits_agglomeration.ipynb",
      "size": 3104,
      "type": "notebook",
      "writable": true
    },
    {
      "content": null,
      "created": "2025-12-23T21:33:23.512459Z",
      "format": null,
      "hash": null,
      "hash_algorithm": null,
      "last_modified": "2025-12-23T21:33:18.881488Z",
      "mimetype": null,
      "name": "plot_digits_linkage.ipynb",
      "path": "auto_examples/cluster/plot_digits_linkage.ipynb",
      "size": 4279,
      "type": "notebook",
      "writable": true
    },
    {
      "content": null,
      "created": "2025-12-23T21:33:23.512459Z",
      "format": null,
      "hash": null,
      "hash_algorithm": null,
      "last_modified": "2025-12-23T21:33:18.882488Z",
      "mimetype": null,
      "name": "plot_face_compress.ipynb",
      "path": "auto_examples/cluster/plot_face_compress.ipynb",
      "size": 11000,
      "type": "notebook",
      "writable": true
    },
    {
      "content": null,
      "created": "2025-12-23T21:33:23.513459Z",
      "format": null,
      "hash": null,
      "hash_algorithm": null,
      "last_modified": "2025-12-23T21:33:18.882488Z",
      "mimetype": null,
      "name": "plot_feature_agglomeration_vs_univariate_selection.ipynb",
      "path": "auto_examples/cluster/plot_feature_agglomeration_vs_univariate_selection.ipynb",
      "size": 7597,
      "type": "notebook",
      "writable": true
    },
    {
      "content": null,
      "created": "2025-12-23T21:33:23.513459Z",
      "format": null,
      "hash": null,
      "hash_algorithm": null,
      "last_modified": "2025-12-23T21:33:18.883488Z",
      "mimetype": null,
      "name": "plot_hdbscan.ipynb",
      "path": "auto_examples/cluster/plot_hdbscan.ipynb",
      "size": 14467,
      "type": "notebook",
      "writable": true
    },
    {
      "content": null,
      "created": "2025-12-23T21:33:23.513459Z",
      "format": null,
      "hash": null,
      "hash_algorithm": null,
      "last_modified": "2025-12-23T21:33:18.884488Z",
      "mimetype": null,
      "name": "plot_inductive_clustering.ipynb",
      "path": "auto_examples/cluster/plot_inductive_clustering.ipynb",
      "size": 5634,
      "type": "notebook",
      "writable": true
    },
    {
      "content": null,
      "created": "2025-12-23T21:33:23.514459Z",
      "format": null,
      "hash": null,
      "hash_algorithm": null,
      "last_modified": "2025-12-23T21:33:18.884488Z",
      "mimetype": null,
      "name": "plot_kmeans_assumptions.ipynb",
      "path": "auto_examples/cluster/plot_kmeans_assumptions.ipynb",
      "size": 9877,
      "type": "notebook",
      "writable": true
    },
    {
      "content": null,
      "created": "2025-12-23T21:33:23.514459Z",
      "format": null,
      "hash": null,
      "hash_algorithm": null,
      "last_modified": "2025-12-23T21:33:18.885488Z",
      "mimetype": null,
      "name": "plot_kmeans_digits.ipynb",
      "path": "auto_examples/cluster/plot_kmeans_digits.ipynb",
      "size": 9555,
      "type": "notebook",
      "writable": true
    },
    {
      "content": null,
      "created": "2025-12-23T21:33:23.514459Z",
      "format": null,
      "hash": null,
      "hash_algorithm": null,
      "last_modified": "2025-12-23T21:33:18.885488Z",
      "mimetype": null,
      "name": "plot_kmeans_plusplus.ipynb",
      "path": "auto_examples/cluster/plot_kmeans_plusplus.ipynb",
      "size": 2753,
      "type": "notebook",
      "writable": true
    },
    {
      "content": null,
      "created": "2025-12-23T21:33:23.515459Z",
      "format": null,
      "hash": null,
      "hash_algorithm": null,
      "last_modified": "2025-12-23T21:33:18.886488Z",
      "mimetype": null,
      "name": "plot_kmeans_silhouette_analysis.ipynb",
      "path": "auto_examples/cluster/plot_kmeans_silhouette_analysis.ipynb",
      "size": 7588,
      "type": "notebook",
      "writable": true
    },
    {
      "content": null,
      "created": "2025-12-23T21:33:23.515459Z",
      "format": null,
      "hash": null,
      "hash_algorithm": null,
      "last_modified": "2025-12-23T21:33:18.886488Z",
      "mimetype": null,
      "name": "plot_kmeans_stability_low_dim_dense.ipynb",
      "path": "auto_examples/cluster/plot_kmeans_stability_low_dim_dense.ipynb",
      "size": 5969,
      "type": "notebook",
      "writable": true
    },
    {
      "content": null,
      "created": "2025-12-23T21:33:23.516459Z",
      "format": null,
      "hash": null,
      "hash_algorithm": null,
      "last_modified": "2025-12-23T21:33:18.887488Z",
      "mimetype": null,
      "name": "plot_linkage_comparison.ipynb",
      "path": "auto_examples/cluster/plot_linkage_comparison.ipynb",
      "size": 7482,
      "type": "notebook",
      "writable": true
    },
    {
      "content": null,
      "created": "2025-12-23T21:33:23.516459Z",
      "format": null,
      "hash": null,
      "hash_algorithm": null,
      "last_modified": "2025-12-23T21:33:18.887488Z",
      "mimetype": null,
      "name": "plot_mean_shift.ipynb",
      "path": "auto_examples/cluster/plot_mean_shift.ipynb",
      "size": 4077,
      "type": "notebook",
      "writable": true
    },
    {
      "content": null,
      "created": "2025-12-23T21:33:23.516459Z",
      "format": null,
      "hash": null,
      "hash_algorithm": null,
      "last_modified": "2025-12-23T21:33:18.888488Z",
      "mimetype": null,
      "name": "plot_mini_batch_kmeans.ipynb",
      "path": "auto_examples/cluster/plot_mini_batch_kmeans.ipynb",
      "size": 6953,
      "type": "notebook",
      "writable": true
    },
    {
      "content": null,
      "created": "2025-12-23T21:33:23.517459Z",
      "format": null,
      "hash": null,
      "hash_algorithm": null,
      "last_modified": "2025-12-23T21:33:18.888488Z",
      "mimetype": null,
      "name": "plot_optics.ipynb",
      "path": "auto_examples/cluster/plot_optics.ipynb",
      "size": 5139,
      "type": "notebook",
      "writable": true
    },
    {
      "content": null,
      "created": "2025-12-23T21:33:23.517459Z",
      "format": null,
      "hash": null,
      "hash_algorithm": null,
      "last_modified": "2025-12-23T21:33:18.889488Z",
      "mimetype": null,
      "name": "plot_segmentation_toy.ipynb",
      "path": "auto_examples/cluster/plot_segmentation_toy.ipynb",
      "size": 6923,
      "type": "notebook",
      "writable": true
    },
    {
      "content": null,
      "created": "2025-12-23T21:33:23.517459Z",
      "format": null,
      "hash": null,
      "hash_algorithm": null,
      "last_modified": "2025-12-23T21:33:18.890488Z",
      "mimetype": null,
      "name": "plot_ward_structured_vs_unstructured.ipynb",
      "path": "auto_examples/cluster/plot_ward_structured_vs_unstructured.ipynb",
      "size": 10182,
      "type": "notebook",
      "writable": true
    }
  ],
  "created": "2025-12-23T21:33:23.517459Z",
  "format": "json",
  "hash": null,
  "hash_algorithm": null,
  "last_modified": "2025-12-23T21:33:23.517459Z",
  "mimetype": null,
  "name": "cluster",
  "path": "auto_examples/cluster",
  "size": null,
  "type": "directory",
  "writable": true
}