{
  "content": [
    {
      "content": null,
      "created": "2025-02-20T07:57:05.666619Z",
      "format": null,
      "hash": null,
      "hash_algorithm": null,
      "last_modified": "2025-02-20T07:57:05.666619Z",
      "mimetype": null,
      "name": "auto_examples",
      "path": "auto_examples",
      "size": null,
      "type": "directory",
      "writable": true
    }
  ],
  "created": "2025-02-20T07:57:05.551618Z",
  "format": "json",
  "hash": null,
  "hash_algorithm": null,
  "last_modified": "2025-02-20T07:57:05.551618Z",
  "mimetype": null,
  "name": "",
  "path": "",
  "size": null,
  "type": "directory",
  "writable": true
}