{
  "content": [
    {
      "content": null,
      "created": "2025-02-20T07:57:05.598618Z",
      "format": null,
      "hash": null,
      "hash_algorithm": null,
      "last_modified": "2025-02-20T07:57:01.865597Z",
      "mimetype": null,
      "name": "plot_compare_gpr_krr.ipynb",
      "path": "auto_examples/gaussian_process/plot_compare_gpr_krr.ipynb",
      "size": 19312,
      "type": "notebook",
      "writable": true
    },
    {
      "content": null,
      "created": "2025-02-20T07:57:05.598618Z",
      "format": null,
      "hash": null,
      "hash_algorithm": null,
      "last_modified": "2025-02-20T07:57:01.865597Z",
      "mimetype": null,
      "name": "plot_gpc.ipynb",
      "path": "auto_examples/gaussian_process/plot_gpc.ipynb",
      "size": 5591,
      "type": "notebook",
      "writable": true
    },
    {
      "content": null,
      "created": "2025-02-20T07:57:05.599618Z",
      "format": null,
      "hash": null,
      "hash_algorithm": null,
      "last_modified": "2025-02-20T07:57:01.865597Z",
      "mimetype": null,
      "name": "plot_gpc_iris.ipynb",
      "path": "auto_examples/gaussian_process/plot_gpc_iris.ipynb",
      "size": 3845,
      "type": "notebook",
      "writable": true
    },
    {
      "content": null,
      "created": "2025-02-20T07:57:05.599618Z",
      "format": null,
      "hash": null,
      "hash_algorithm": null,
      "last_modified": "2025-02-20T07:57:01.866597Z",
      "mimetype": null,
      "name": "plot_gpc_isoprobability.ipynb",
      "path": "auto_examples/gaussian_process/plot_gpc_isoprobability.ipynb",
      "size": 4403,
      "type": "notebook",
      "writable": true
    },
    {
      "content": null,
      "created": "2025-02-20T07:57:05.599618Z",
      "format": null,
      "hash": null,
      "hash_algorithm": null,
      "last_modified": "2025-02-20T07:57:01.866597Z",
      "mimetype": null,
      "name": "plot_gpc_xor.ipynb",
      "path": "auto_examples/gaussian_process/plot_gpc_xor.ipynb",
      "size": 3592,
      "type": "notebook",
      "writable": true
    },
    {
      "content": null,
      "created": "2025-02-20T07:57:05.600618Z",
      "format": null,
      "hash": null,
      "hash_algorithm": null,
      "last_modified": "2025-02-20T07:57:01.867597Z",
      "mimetype": null,
      "name": "plot_gpr_co2.ipynb",
      "path": "auto_examples/gaussian_process/plot_gpr_co2.ipynb",
      "size": 14449,
      "type": "notebook",
      "writable": true
    },
    {
      "content": null,
      "created": "2025-02-20T07:57:05.600618Z",
      "format": null,
      "hash": null,
      "hash_algorithm": null,
      "last_modified": "2025-02-20T07:57:01.868597Z",
      "mimetype": null,
      "name": "plot_gpr_noisy.ipynb",
      "path": "auto_examples/gaussian_process/plot_gpr_noisy.ipynb",
      "size": 12651,
      "type": "notebook",
      "writable": true
    },
    {
      "content": null,
      "created": "2025-02-20T07:57:05.601618Z",
      "format": null,
      "hash": null,
      "hash_algorithm": null,
      "last_modified": "2025-02-20T07:57:01.869597Z",
      "mimetype": null,
      "name": "plot_gpr_noisy_targets.ipynb",
      "path": "auto_examples/gaussian_process/plot_gpr_noisy_targets.ipynb",
      "size": 8871,
      "type": "notebook",
      "writable": true
    },
    {
      "content": null,
      "created": "2025-02-20T07:57:05.601618Z",
      "format": null,
      "hash": null,
      "hash_algorithm": null,
      "last_modified": "2025-02-20T07:57:01.870597Z",
      "mimetype": null,
      "name": "plot_gpr_on_structured_data.ipynb",
      "path": "auto_examples/gaussian_process/plot_gpr_on_structured_data.ipynb",
      "size": 8513,
      "type": "notebook",
      "writable": true
    },
    {
      "content": null,
      "created": "2025-02-20T07:57:05.601618Z",
      "format": null,
      "hash": null,
      "hash_algorithm": null,
      "last_modified": "2025-02-20T07:57:01.871597Z",
      "mimetype": null,
      "name": "plot_gpr_prior_posterior.ipynb",
      "path": "auto_examples/gaussian_process/plot_gpr_prior_posterior.ipynb",
      "size": 12822,
      "type": "notebook",
      "writable": true
    }
  ],
  "created": "2025-02-20T07:57:05.601618Z",
  "format": "json",
  "hash": null,
  "hash_algorithm": null,
  "last_modified": "2025-02-20T07:57:05.601618Z",
  "mimetype": null,
  "name": "gaussian_process",
  "path": "auto_examples/gaussian_process",
  "size": null,
  "type": "directory",
  "writable": true
}