{
  "content": [
    {
      "content": null,
      "created": "2026-06-02T13:02:38.046072Z",
      "format": null,
      "hash": null,
      "hash_algorithm": null,
      "last_modified": "2026-06-02T13:02:33.270833Z",
      "mimetype": null,
      "name": "sklearn_is_fitted.ipynb",
      "path": "auto_examples/developing_estimators/sklearn_is_fitted.ipynb",
      "size": 4223,
      "type": "notebook",
      "writable": true
    }
  ],
  "created": "2026-06-02T13:02:38.046072Z",
  "format": "json",
  "hash": null,
  "hash_algorithm": null,
  "last_modified": "2026-06-02T13:02:38.046072Z",
  "mimetype": null,
  "name": "developing_estimators",
  "path": "auto_examples/developing_estimators",
  "size": null,
  "type": "directory",
  "writable": true
}